funcat/VERSION.txt
funcat/__init__.py
funcat/api.py
funcat/context.py
funcat/func.py
funcat/helper.py
funcat/indicators.py
funcat/time_series.py
funcat/conditional_selection/__init__.py
funcat/conditional_selection/selection.py
funcat/conditional_selection/turtle.py
funcat/data/__init__.py
funcat/data/backend.py
funcat/data/mongodb_backend.py
funcat/data/quantaxis_backend.py
funcat/data/rqalpha_data_backend.py
funcat/data/rqdata_data_backend.py
funcat/data/rt_data_from_tencent.py
funcat/data/tencent_backend.py
funcat/data/test_tencent_api.py
funcat/data/tushare_backend.py
funcat/data/tusharepro_backend.py
funcat/strategy/__init__.py
funcat/utils/__init__.py
funcat/utils/async_utils.py
funcat/utils/delist.py
funcat/utils/singletion.py
funcat/utils/tdx2python.py
funcat/utils/test_base.py
funcat/utils/util.py
tests/__init__.py
tests/funcat/__init__.py
tests/funcat/test_api.py
tests/funcat/test_ema_trends.py
tests/funcat/test_funcat2.py
tests/funcat/test_quantaxis_api.py
tests/funcat/test_utils.py
tests/funcat/conditional_selection/__init__.py
tests/funcat/conditional_selection/test_selection.py
tests/funcat/conditional_selection/test_turtle.py
tests/funcat/data/__init__.py
tests/funcat/data/test_mongodb_backend.py
tests/funcat/data/test_quantaxis_backend.py
tests/funcat/data/test_tushare_api.py
tests/funcat/data/test_tusharepro_backend.py
tests/funcat/others/__init__.py
tests/funcat/others/clustering.md
tests/funcat/others/plot_dbscan.py
tests/funcat/others/plot_stock_SZ50_market.py
tests/funcat/others/plot_stock_market.md
tests/funcat/others/plot_stock_market.py
tests/funcat/utils/__init__.py
tests/funcat/utils/test_tdx2python.py
funcat2-0.4.3.dist-info/LICENSE
funcat2-0.4.3.dist-info/METADATA
funcat2-0.4.3.dist-info/WHEEL
funcat2-0.4.3.dist-info/top_level.txt
funcat2-0.4.3.dist-info/RECORD
